<?xml version="1.0" encoding="UTF-8"?><record_update sys_domain="global" table="asmt_metric_category">
    <asmt_metric_category action="INSERT_OR_UPDATE">
        <create_stakeholders>false</create_stakeholders>
        <description>ServiceNow </description>
        <details><![CDATA[<p>ServiceNow </p>]]></details>
        <filter table="x_306761_training_training_records">state=in_progress^EQ<item display_value="In Progress" endquery="false" field="state" goto="false" newquery="false" operator="=" or="false" value="in_progress"/>
            <item endquery="true" field="" goto="false" newquery="false" operator="=" or="false" value=""/>
        </filter>
        <metric_type display_value="ServiceNow Assessment">eadf62289736e590f294b998c253afff</metric_type>
        <name>ServiceNow </name>
        <order>1</order>
        <qb_evaluation_method/>
        <roles/>
        <scoring_type>percent</scoring_type>
        <sys_class_name>asmt_metric_category</sys_class_name>
        <sys_created_by>admin</sys_created_by>
        <sys_created_on>2023-05-11 07:14:06</sys_created_on>
        <sys_domain>global</sys_domain>
        <sys_domain_path>/</sys_domain_path>
        <sys_id>d932f6e4977ae590f294b998c253af8d</sys_id>
        <sys_mod_count>4</sys_mod_count>
        <sys_name>ServiceNow </sys_name>
        <sys_package display_value="Training Record" source="x_306761_training">5ee7579c97f2e910f294b998c253afca</sys_package>
        <sys_policy/>
        <sys_scope display_value="Training Record">5ee7579c97f2e910f294b998c253afca</sys_scope>
        <sys_update_name>asmt_metric_category_d932f6e4977ae590f294b998c253af8d</sys_update_name>
        <sys_updated_by>admin</sys_updated_by>
        <sys_updated_on>2023-05-12 18:07:17</sys_updated_on>
        <table>x_306761_training_training_records</table>
        <total_metrics>1</total_metrics>
        <weight>10</weight>
    </asmt_metric_category>
    <sys_translated_text action="delete_multiple" query="documentkey=d932f6e4977ae590f294b998c253af8d"/>
</record_update>
